pydictnest/__init__.py
pydictnest/nested_utils.py
pydictnest-0.2.1.dist-info/licenses/LICENSE
pydictnest-0.2.1.dist-info/METADATA
pydictnest-0.2.1.dist-info/WHEEL
pydictnest-0.2.1.dist-info/top_level.txt
pydictnest-0.2.1.dist-info/RECORD
