Metadata-Version: 2.4
Name: pydictnest
Version: 0.2.1
Summary: A small package, which provides functions for working with nested dictionaries.
Author-email: Moritz Sallermann <moritzsallermann@gmail.com>
License-Expression: MIT
Project-URL: Homepage, https://github.com/MSallermann/pydictnest
Project-URL: Issues, https://github.com/MSallermann/pydictnest/issues
Classifier: Programming Language :: Python :: 3
Classifier: Operating System :: OS Independent
Requires-Python: >=3.9
License-File: LICENSE
Dynamic: license-file
